{
    "AvailabilityQuestId": -1,
    "DialogHideNPC": 0b,
    "AvailabilityQuest2": 0,
    "AvailabilityQuest3": 0,
    "AvailabilityQuest4": 0,
    "RenderGradual": 0b,
    "OptionOffsetX": 0,
    "OptionOffsetY": 0,
    "OptionFactions1": -1,
    "TextOffsetX": 0,
    "OptionFactions2": -1,
    "TextOffsetY": 0,
    "AvailabilityFaction2Id": -1,
    "TitlePos": 0,
    "OptionFaction1Points": 100,
    "TitleColor": 14737632,
    "DialogDisableEsc": 0b,
    "ShowOptionLine": 1b,
    "AvailabilityFaction": 0,
    "AvailabilityDialog": 0,
    "AvailabilityFaction2": 0,
    "Color": 14737632,
    "Images": [
    ],
    "NPCScale": 1.0f,
    "TextSound": "minecraft:random.wood_click",
    "AvailabilityFactionId": -1,
    "AvailabilityFaction2Stance": 0,
    "DialogCommand": "",
    "TextPitch": 1.0f,
    "AvailabilityDialogId": -1,
    "OptionFaction2Points": 100,
    "AvailabilityQuest3Id": -1,
    "NPCOffsetY": 0,
    "AvailabilityDialog3Id": -1,
    "NPCOffsetX": 0,
    "AvailabilityMinPlayerLevel": 0,
    "DecreaseFaction2Points": 0b,
    "DialogShowWheel": 0b,
    "Options": [
        {
            "OptionSlot": 0,
            "Option": {
                "DialogCommand": "",
                "Dialog": 204,
                "Title": "告诉我更多关于风云丘陵的事。",
                "DialogColor": 15065358,
                "OptionType": 1
            }
        },
        {
            "OptionSlot": 1,
            "Option": {
                "DialogCommand": "",
                "Dialog": -1,
                "Title": "再会!",
                "DialogColor": 16516869,
                "OptionType": 0
            }
        }
    ],
    "TextHeight": 400,
    "OptionSpaceX": 0,
    "AvailabilityFactionStance": 0,
    "AvailabilityQuest": 0,
    "AvailabilityDialog4": 0,
    "AvailabilityDialog3": 0,
    "OptionSpaceY": 0,
    "TitleOffsetY": 0,
    "TitleOffsetX": 0,
    "ModRev": 19,
    "DecreaseFaction1Points": 0b,
    "DialogQuest": -1,
    "AvailabilityDialog2": 0,
    "AvailabilityDayTime": 0,
    "DialogDarkScreen": 1b,
    "TextWidth": 300,
    "DialogTitle": "aragorn elrond",
    "PreviousBlocks": 1b,
    "DialogText": "埃尔隆德是幽谷的精灵之主。幽谷是埃瑞吉安精灵之家，也是中洲最美丽的地方之一。
我小时候在那里生活了很长时间，并学会了精灵的语言。
伊姆拉缀斯的人民是自豪的，埃尔隆德领主很有智慧。他会知道该如何处理这枚戒指的。
我们将在那里相会！",
    "AvailabilityQuest4Id": -1,
    "AvailabilityQuest2Id": -1,
    "AvailabilityDialog2Id": -1,
    "AvailabilityDialog4Id": -1,
    "DialogMail": {
        "Sender": "",
        "BeenRead": 0b,
        "Message": {
        },
        "MailItems": [
        ],
        "MailQuest": -1,
        "TimePast": 1690133710264L,
        "Time": 0L,
        "Subject": ""
    }
}
